{
  "openapi": "3.0.1",
  "info": {
    "title": "PokerGenys API",
    "description": "API para gestión de Torneos y Mesas Cash en Tiempo Real",
    "version": "v1"
  },
  "paths": {
    "/api/dealers": {
      "get": {
        "tags": [
          "Dealers"
        ],
        "responses": {
          "200": {
            "description": "OK"
          }
        }
      }
    },
    "/api/dealer-shifts": {
      "get": {
        "tags": [
          "Dealers"
        ],
        "parameters": [
          {
            "name": "dayId",
            "in": "query",
            "schema": {
              "type": "string",
              "format": "uuid"
            }
          },
          {
            "name": "tableId",
            "in": "query",
            "schema": {
              "type": "string",
              "format": "uuid"
            }
          }
        ],
        "responses": {
          "200": {
            "description": "OK"
          }
        }
      },
      "post": {
        "tags": [
          "Dealers"
        ],
        "requestBody": {
          "content": {
            "application/json": {
              "schema": {
                "$ref": "#/components/schemas/PokerGenys.Domain.Models.DealerShift"
              }
            },
            "text/json": {
              "schema": {
                "$ref": "#/components/schemas/PokerGenys.Domain.Models.DealerShift"
              }
            },
            "application/*+json": {
              "schema": {
                "$ref": "#/components/schemas/PokerGenys.Domain.Models.DealerShift"
              }
            }
          }
        },
        "responses": {
          "200": {
            "description": "OK"
          }
        }
      }
    },
    "/api/dealer-shifts/{id}": {
      "put": {
        "tags": [
          "Dealers"
        ],
        "parameters": [
          {
            "name": "id",
            "in": "path",
            "required": true,
            "schema": {
              "type": "string",
              "format": "uuid"
            }
          }
        ],
        "requestBody": {
          "content": {
            "application/json": {
              "schema": {
                "$ref": "#/components/schemas/PokerGenys.Domain.Models.DealerShift"
              }
            },
            "text/json": {
              "schema": {
                "$ref": "#/components/schemas/PokerGenys.Domain.Models.DealerShift"
              }
            },
            "application/*+json": {
              "schema": {
                "$ref": "#/components/schemas/PokerGenys.Domain.Models.DealerShift"
              }
            }
          }
        },
        "responses": {
          "200": {
            "description": "OK"
          }
        }
      }
    },
    "/api/players": {
      "get": {
        "tags": [
          "Players"
        ],
        "responses": {
          "200": {
            "description": "OK"
          }
        }
      },
      "post": {
        "tags": [
          "Players"
        ],
        "requestBody": {
          "content": {
            "application/json": {
              "schema": {
                "$ref": "#/components/schemas/PokerGenys.Domain.Models.Player"
              }
            },
            "text/json": {
              "schema": {
                "$ref": "#/components/schemas/PokerGenys.Domain.Models.Player"
              }
            },
            "application/*+json": {
              "schema": {
                "$ref": "#/components/schemas/PokerGenys.Domain.Models.Player"
              }
            }
          }
        },
        "responses": {
          "200": {
            "description": "OK"
          }
        }
      }
    },
    "/api/players/{id}": {
      "get": {
        "tags": [
          "Players"
        ],
        "parameters": [
          {
            "name": "id",
            "in": "path",
            "required": true,
            "schema": {
              "type": "string",
              "format": "uuid"
            }
          }
        ],
        "responses": {
          "200": {
            "description": "OK"
          }
        }
      },
      "put": {
        "tags": [
          "Players"
        ],
        "parameters": [
          {
            "name": "id",
            "in": "path",
            "required": true,
            "schema": {
              "type": "string",
              "format": "uuid"
            }
          }
        ],
        "requestBody": {
          "content": {
            "application/json": {
              "schema": {
                "$ref": "#/components/schemas/PokerGenys.Domain.Models.Player"
              }
            },
            "text/json": {
              "schema": {
                "$ref": "#/components/schemas/PokerGenys.Domain.Models.Player"
              }
            },
            "application/*+json": {
              "schema": {
                "$ref": "#/components/schemas/PokerGenys.Domain.Models.Player"
              }
            }
          }
        },
        "responses": {
          "200": {
            "description": "OK"
          }
        }
      },
      "delete": {
        "tags": [
          "Players"
        ],
        "parameters": [
          {
            "name": "id",
            "in": "path",
            "required": true,
            "schema": {
              "type": "string",
              "format": "uuid"
            }
          }
        ],
        "responses": {
          "200": {
            "description": "OK"
          }
        }
      }
    },
    "/api/sessions": {
      "get": {
        "tags": [
          "Sessions"
        ],
        "responses": {
          "200": {
            "description": "OK"
          }
        }
      },
      "post": {
        "tags": [
          "Sessions"
        ],
        "requestBody": {
          "content": {
            "application/json": {
              "schema": {
                "$ref": "#/components/schemas/PokerGenys.Domain.Models.Session"
              }
            },
            "text/json": {
              "schema": {
                "$ref": "#/components/schemas/PokerGenys.Domain.Models.Session"
              }
            },
            "application/*+json": {
              "schema": {
                "$ref": "#/components/schemas/PokerGenys.Domain.Models.Session"
              }
            }
          }
        },
        "responses": {
          "200": {
            "description": "OK"
          }
        }
      }
    },
    "/api/sessions/{id}": {
      "put": {
        "tags": [
          "Sessions"
        ],
        "parameters": [
          {
            "name": "id",
            "in": "path",
            "required": true,
            "schema": {
              "type": "string",
              "format": "uuid"
            }
          }
        ],
        "requestBody": {
          "content": {
            "application/json": {
              "schema": {
                "$ref": "#/components/schemas/PokerGenys.Domain.Models.Session"
              }
            },
            "text/json": {
              "schema": {
                "$ref": "#/components/schemas/PokerGenys.Domain.Models.Session"
              }
            },
            "application/*+json": {
              "schema": {
                "$ref": "#/components/schemas/PokerGenys.Domain.Models.Session"
              }
            }
          }
        },
        "responses": {
          "200": {
            "description": "OK"
          }
        }
      }
    },
    "/api/tables": {
      "get": {
        "tags": [
          "Tables"
        ],
        "parameters": [
          {
            "name": "dayId",
            "in": "query",
            "schema": {
              "type": "string",
              "format": "uuid"
            }
          }
        ],
        "responses": {
          "200": {
            "description": "OK"
          }
        }
      },
      "post": {
        "tags": [
          "Tables"
        ],
        "requestBody": {
          "content": {
            "application/json": {
              "schema": {
                "$ref": "#/components/schemas/PokerGenys.Domain.Models.TableInstance"
              }
            },
            "text/json": {
              "schema": {
                "$ref": "#/components/schemas/PokerGenys.Domain.Models.TableInstance"
              }
            },
            "application/*+json": {
              "schema": {
                "$ref": "#/components/schemas/PokerGenys.Domain.Models.TableInstance"
              }
            }
          }
        },
        "responses": {
          "200": {
            "description": "OK"
          }
        }
      }
    },
    "/api/tables/{id}": {
      "put": {
        "tags": [
          "Tables"
        ],
        "parameters": [
          {
            "name": "id",
            "in": "path",
            "required": true,
            "schema": {
              "type": "string",
              "format": "uuid"
            }
          }
        ],
        "requestBody": {
          "content": {
            "application/json": {
              "schema": {
                "$ref": "#/components/schemas/PokerGenys.Domain.Models.TableInstance"
              }
            },
            "text/json": {
              "schema": {
                "$ref": "#/components/schemas/PokerGenys.Domain.Models.TableInstance"
              }
            },
            "application/*+json": {
              "schema": {
                "$ref": "#/components/schemas/PokerGenys.Domain.Models.TableInstance"
              }
            }
          }
        },
        "responses": {
          "200": {
            "description": "OK"
          }
        }
      }
    },
    "/api/Test/ping": {
      "get": {
        "tags": [
          "Test"
        ],
        "responses": {
          "200": {
            "description": "OK"
          }
        }
      }
    },
    "/api/Tournaments": {
      "get": {
        "tags": [
          "Tournaments"
        ],
        "responses": {
          "200": {
            "description": "OK"
          }
        }
      },
      "post": {
        "tags": [
          "Tournaments"
        ],
        "requestBody": {
          "content": {
            "application/json": {
              "schema": {
                "$ref": "#/components/schemas/PokerGenys.Domain.Models.Tournament"
              }
            },
            "text/json": {
              "schema": {
                "$ref": "#/components/schemas/PokerGenys.Domain.Models.Tournament"
              }
            },
            "application/*+json": {
              "schema": {
                "$ref": "#/components/schemas/PokerGenys.Domain.Models.Tournament"
              }
            }
          }
        },
        "responses": {
          "200": {
            "description": "OK"
          }
        }
      }
    },
    "/api/Tournaments/{id}": {
      "get": {
        "tags": [
          "Tournaments"
        ],
        "parameters": [
          {
            "name": "id",
            "in": "path",
            "required": true,
            "schema": {
              "type": "string",
              "format": "uuid"
            }
          }
        ],
        "responses": {
          "200": {
            "description": "OK"
          }
        }
      },
      "put": {
        "tags": [
          "Tournaments"
        ],
        "parameters": [
          {
            "name": "id",
            "in": "path",
            "required": true,
            "schema": {
              "type": "string",
              "format": "uuid"
            }
          }
        ],
        "requestBody": {
          "content": {
            "application/json": {
              "schema": {
                "$ref": "#/components/schemas/PokerGenys.Domain.Models.Tournament"
              }
            },
            "text/json": {
              "schema": {
                "$ref": "#/components/schemas/PokerGenys.Domain.Models.Tournament"
              }
            },
            "application/*+json": {
              "schema": {
                "$ref": "#/components/schemas/PokerGenys.Domain.Models.Tournament"
              }
            }
          }
        },
        "responses": {
          "200": {
            "description": "OK"
          }
        }
      },
      "patch": {
        "tags": [
          "Tournaments"
        ],
        "parameters": [
          {
            "name": "id",
            "in": "path",
            "required": true,
            "schema": {
              "type": "string",
              "format": "uuid"
            }
          }
        ],
        "requestBody": {
          "content": {
            "application/json": {
              "schema": { }
            },
            "text/json": {
              "schema": { }
            },
            "application/*+json": {
              "schema": { }
            }
          }
        },
        "responses": {
          "200": {
            "description": "OK"
          }
        }
      },
      "delete": {
        "tags": [
          "Tournaments"
        ],
        "parameters": [
          {
            "name": "id",
            "in": "path",
            "required": true,
            "schema": {
              "type": "string",
              "format": "uuid"
            }
          }
        ],
        "responses": {
          "200": {
            "description": "OK"
          }
        }
      }
    },
    "/api/Tournaments/{id}/registrations": {
      "get": {
        "tags": [
          "Tournaments"
        ],
        "parameters": [
          {
            "name": "id",
            "in": "path",
            "required": true,
            "schema": {
              "type": "string",
              "format": "uuid"
            }
          }
        ],
        "responses": {
          "200": {
            "description": "OK"
          }
        }
      },
      "post": {
        "tags": [
          "Tournaments"
        ],
        "parameters": [
          {
            "name": "id",
            "in": "path",
            "required": true,
            "schema": {
              "type": "string",
              "format": "uuid"
            }
          }
        ],
        "requestBody": {
          "content": {
            "application/json": {
              "schema": {
                "$ref": "#/components/schemas/PokerGenys.Domain.Models.TournamentRegistration"
              }
            },
            "text/json": {
              "schema": {
                "$ref": "#/components/schemas/PokerGenys.Domain.Models.TournamentRegistration"
              }
            },
            "application/*+json": {
              "schema": {
                "$ref": "#/components/schemas/PokerGenys.Domain.Models.TournamentRegistration"
              }
            }
          }
        },
        "responses": {
          "200": {
            "description": "OK"
          }
        }
      }
    },
    "/api/Tournaments/{id}/registrations/{regId}": {
      "delete": {
        "tags": [
          "Tournaments"
        ],
        "parameters": [
          {
            "name": "id",
            "in": "path",
            "required": true,
            "schema": {
              "type": "string",
              "format": "uuid"
            }
          },
          {
            "name": "regId",
            "in": "path",
            "required": true,
            "schema": {
              "type": "string",
              "format": "uuid"
            }
          }
        ],
        "responses": {
          "200": {
            "description": "OK"
          }
        }
      }
    },
    "/api/Tournaments/{id}/registrations/{regId}/seat": {
      "post": {
        "tags": [
          "Tournaments"
        ],
        "parameters": [
          {
            "name": "id",
            "in": "path",
            "required": true,
            "schema": {
              "type": "string",
              "format": "uuid"
            }
          },
          {
            "name": "regId",
            "in": "path",
            "required": true,
            "schema": {
              "type": "string",
              "format": "uuid"
            }
          }
        ],
        "requestBody": {
          "content": {
            "application/json": {
              "schema": {
                "$ref": "#/components/schemas/PokerGenys.API.Controllers.TournamentsController+SeatRequest"
              }
            },
            "text/json": {
              "schema": {
                "$ref": "#/components/schemas/PokerGenys.API.Controllers.TournamentsController+SeatRequest"
              }
            },
            "application/*+json": {
              "schema": {
                "$ref": "#/components/schemas/PokerGenys.API.Controllers.TournamentsController+SeatRequest"
              }
            }
          }
        },
        "responses": {
          "200": {
            "description": "OK"
          }
        }
      }
    },
    "/api/Tournaments/{id}/start": {
      "post": {
        "tags": [
          "Tournaments"
        ],
        "parameters": [
          {
            "name": "id",
            "in": "path",
            "required": true,
            "schema": {
              "type": "string",
              "format": "uuid"
            }
          }
        ],
        "responses": {
          "200": {
            "description": "OK"
          }
        }
      }
    },
    "/api/Tournaments/{id}/state": {
      "get": {
        "tags": [
          "Tournaments"
        ],
        "parameters": [
          {
            "name": "id",
            "in": "path",
            "required": true,
            "schema": {
              "type": "string",
              "format": "uuid"
            }
          }
        ],
        "responses": {
          "200": {
            "description": "OK"
          }
        }
      }
    },
    "/api/Tournaments/{id}/register": {
      "post": {
        "tags": [
          "Tournaments"
        ],
        "parameters": [
          {
            "name": "id",
            "in": "path",
            "required": true,
            "schema": {
              "type": "string",
              "format": "uuid"
            }
          }
        ],
        "requestBody": {
          "content": {
            "application/json": {
              "schema": {
                "type": "string"
              }
            },
            "text/json": {
              "schema": {
                "type": "string"
              }
            },
            "application/*+json": {
              "schema": {
                "type": "string"
              }
            }
          }
        },
        "responses": {
          "200": {
            "description": "OK"
          }
        }
      }
    },
    "/api/waitlist": {
      "get": {
        "tags": [
          "Waitlist"
        ],
        "parameters": [
          {
            "name": "tableId",
            "in": "query",
            "schema": {
              "type": "string",
              "format": "uuid"
            }
          }
        ],
        "responses": {
          "200": {
            "description": "OK"
          }
        }
      },
      "post": {
        "tags": [
          "Waitlist"
        ],
        "requestBody": {
          "content": {
            "application/json": {
              "schema": {
                "$ref": "#/components/schemas/PokerGenys.API.Controllers.WaitlistController+AddWaitlistRequest"
              }
            },
            "text/json": {
              "schema": {
                "$ref": "#/components/schemas/PokerGenys.API.Controllers.WaitlistController+AddWaitlistRequest"
              }
            },
            "application/*+json": {
              "schema": {
                "$ref": "#/components/schemas/PokerGenys.API.Controllers.WaitlistController+AddWaitlistRequest"
              }
            }
          }
        },
        "responses": {
          "200": {
            "description": "OK"
          }
        }
      }
    },
    "/api/waitlist/{id}": {
      "delete": {
        "tags": [
          "Waitlist"
        ],
        "parameters": [
          {
            "name": "id",
            "in": "path",
            "required": true,
            "schema": {
              "type": "string",
              "format": "uuid"
            }
          }
        ],
        "responses": {
          "200": {
            "description": "OK"
          }
        }
      }
    },
    "/api/waitlist/{id}/seat": {
      "post": {
        "tags": [
          "Waitlist"
        ],
        "parameters": [
          {
            "name": "id",
            "in": "path",
            "required": true,
            "schema": {
              "type": "string",
              "format": "uuid"
            }
          }
        ],
        "responses": {
          "200": {
            "description": "OK"
          }
        }
      }
    },
    "/api/working-days": {
      "get": {
        "tags": [
          "WorkingDays"
        ],
        "responses": {
          "200": {
            "description": "OK"
          }
        }
      },
      "post": {
        "tags": [
          "WorkingDays"
        ],
        "responses": {
          "200": {
            "description": "OK"
          }
        }
      }
    },
    "/api/working-days/{id}/close": {
      "patch": {
        "tags": [
          "WorkingDays"
        ],
        "parameters": [
          {
            "name": "id",
            "in": "path",
            "required": true,
            "schema": {
              "type": "string",
              "format": "uuid"
            }
          }
        ],
        "responses": {
          "200": {
            "description": "OK"
          }
        }
      }
    }
  },
  "components": {
    "schemas": {
      "PokerGenys.API.Controllers.TournamentsController+SeatRequest": {
        "type": "object",
        "properties": {
          "tableId": {
            "type": "string",
            "nullable": true
          },
          "seatId": {
            "type": "string",
            "nullable": true
          }
        },
        "additionalProperties": false
      },
      "PokerGenys.API.Controllers.WaitlistController+AddWaitlistRequest": {
        "type": "object",
        "properties": {
          "tableId": {
            "type": "string",
            "format": "uuid"
          },
          "playerId": {
            "type": "string",
            "format": "uuid"
          }
        },
        "additionalProperties": false
      },
      "PokerGenys.Domain.Models.AddonConfig": {
        "type": "object",
        "properties": {
          "enabled": {
            "type": "boolean"
          },
          "addonCost": {
            "type": "number",
            "format": "double"
          },
          "addonHouseFee": {
            "type": "number",
            "format": "double"
          },
          "addonChips": {
            "type": "integer",
            "format": "int32"
          },
          "maxAddonsPerPlayer": {
            "type": "integer",
            "format": "int32"
          },
          "allowedLevel": {
            "type": "integer",
            "format": "int32"
          }
        },
        "additionalProperties": false
      },
      "PokerGenys.Domain.Models.BankMethod": {
        "enum": [
          "Bancolombia",
          "Nequi",
          "Daviplata",
          "Other"
        ],
        "type": "string"
      },
      "PokerGenys.Domain.Models.BlindLevel": {
        "type": "object",
        "properties": {
          "id": {
            "type": "string",
            "format": "uuid"
          },
          "levelNumber": {
            "type": "integer",
            "format": "int32"
          },
          "durationSeconds": {
            "type": "integer",
            "format": "int32"
          },
          "smallBlind": {
            "type": "integer",
            "format": "int32"
          },
          "bigBlind": {
            "type": "integer",
            "format": "int32"
          },
          "ante": {
            "type": "integer",
            "format": "int32"
          },
          "isBreak": {
            "type": "boolean"
          },
          "allowRebuy": {
            "type": "boolean"
          },
          "allowAddon": {
            "type": "boolean"
          }
        },
        "additionalProperties": false
      },
      "PokerGenys.Domain.Models.BountyConfig": {
        "type": "object",
        "properties": {
          "enabled": {
            "type": "boolean"
          },
          "bountyCost": {
            "type": "number",
            "format": "double"
          },
          "prizePerPlayer": {
            "type": "number",
            "format": "double"
          },
          "type": {
            "type": "string",
            "nullable": true
          },
          "progressivePercentage": {
            "type": "number",
            "format": "double"
          }
        },
        "additionalProperties": false
      },
      "PokerGenys.Domain.Models.DealerShift": {
        "type": "object",
        "properties": {
          "id": {
            "type": "string",
            "format": "uuid"
          },
          "dayId": {
            "type": "string",
            "format": "uuid"
          },
          "tableId": {
            "type": "string",
            "format": "uuid"
          },
          "dealerId": {
            "type": "string",
            "format": "uuid"
          },
          "startTime": {
            "type": "string",
            "format": "date-time"
          },
          "endTime": {
            "type": "string",
            "format": "date-time",
            "nullable": true
          },
          "createdAt": {
            "type": "string",
            "format": "date-time"
          },
          "notes": {
            "type": "string",
            "nullable": true
          }
        },
        "additionalProperties": false
      },
      "PokerGenys.Domain.Models.PaymentMethod": {
        "enum": [
          "Cash",
          "Transfer",
          "Courtesy",
          "Saldofavor"
        ],
        "type": "string"
      },
      "PokerGenys.Domain.Models.PaymentStatus": {
        "enum": [
          "Paid",
          "Pending"
        ],
        "type": "string"
      },
      "PokerGenys.Domain.Models.PayoutTier": {
        "type": "object",
        "properties": {
          "id": {
            "type": "string",
            "format": "uuid"
          },
          "rank": {
            "type": "integer",
            "format": "int32"
          },
          "percentage": {
            "type": "number",
            "format": "double"
          },
          "fixedAmount": {
            "type": "number",
            "format": "double"
          }
        },
        "additionalProperties": false
      },
      "PokerGenys.Domain.Models.Player": {
        "type": "object",
        "properties": {
          "id": {
            "type": "string",
            "format": "uuid"
          },
          "name": {
            "type": "string",
            "nullable": true
          },
          "createdAt": {
            "type": "string",
            "format": "date-time"
          }
        },
        "additionalProperties": false
      },
      "PokerGenys.Domain.Models.RebuyConfig": {
        "type": "object",
        "properties": {
          "enabled": {
            "type": "boolean"
          },
          "rebuyCost": {
            "type": "number",
            "format": "double"
          },
          "rebuyHouseFee": {
            "type": "number",
            "format": "double"
          },
          "rebuyChips": {
            "type": "integer",
            "format": "int32"
          },
          "autoRebuy": {
            "type": "boolean"
          },
          "maxRebuysPerPlayer": {
            "type": "integer",
            "format": "int32"
          },
          "untilLevel": {
            "type": "integer",
            "format": "int32"
          }
        },
        "additionalProperties": false
      },
      "PokerGenys.Domain.Models.SeatingConfiguration": {
        "type": "object",
        "properties": {
          "tables": {
            "type": "integer",
            "format": "int32"
          },
          "seatsPerTable": {
            "type": "integer",
            "format": "int32"
          },
          "finalTableSize": {
            "type": "integer",
            "format": "int32"
          },
          "initialSeatingMode": {
            "type": "string",
            "nullable": true
          },
          "tableBalancingMode": {
            "type": "string",
            "nullable": true
          }
        },
        "additionalProperties": false
      },
      "PokerGenys.Domain.Models.Session": {
        "type": "object",
        "properties": {
          "id": {
            "type": "string",
            "format": "uuid"
          },
          "dayId": {
            "type": "string",
            "format": "uuid"
          },
          "tableId": {
            "type": "string",
            "format": "uuid"
          },
          "playerId": {
            "type": "string",
            "format": "uuid"
          },
          "stack": {
            "type": "number",
            "format": "double"
          },
          "startTime": {
            "type": "string",
            "format": "date-time"
          },
          "endTime": {
            "type": "string",
            "format": "date-time",
            "nullable": true
          },
          "initialBuyIn": {
            "type": "number",
            "format": "double"
          },
          "totalInvestment": {
            "type": "number",
            "format": "double"
          },
          "cashOut": {
            "type": "number",
            "format": "double"
          },
          "transactions": {
            "type": "array",
            "items": {
              "$ref": "#/components/schemas/PokerGenys.Domain.Models.Transaction"
            },
            "nullable": true
          },
          "metadata": {
            "type": "object",
            "additionalProperties": { },
            "nullable": true
          },
          "createdAt": {
            "type": "string",
            "format": "date-time"
          }
        },
        "additionalProperties": false
      },
      "PokerGenys.Domain.Models.TableInstance": {
        "type": "object",
        "properties": {
          "id": {
            "type": "string",
            "format": "uuid"
          },
          "dayId": {
            "type": "string",
            "format": "uuid"
          },
          "name": {
            "type": "string",
            "nullable": true
          },
          "status": {
            "$ref": "#/components/schemas/PokerGenys.Domain.Models.TableStatus"
          },
          "maxPlayers": {
            "type": "integer",
            "format": "int32"
          },
          "initialBuyInBase": {
            "type": "number",
            "format": "double"
          },
          "currentDealerId": {
            "type": "string",
            "format": "uuid",
            "nullable": true
          },
          "metadata": {
            "type": "object",
            "additionalProperties": { },
            "nullable": true
          },
          "createdAt": {
            "type": "string",
            "format": "date-time"
          },
          "closedAt": {
            "type": "string",
            "format": "date-time",
            "nullable": true
          }
        },
        "additionalProperties": false
      },
      "PokerGenys.Domain.Models.TableStatus": {
        "enum": [
          "Open",
          "Closed"
        ],
        "type": "string"
      },
      "PokerGenys.Domain.Models.Tournament": {
        "type": "object",
        "properties": {
          "id": {
            "type": "string",
            "format": "uuid"
          },
          "name": {
            "type": "string",
            "nullable": true
          },
          "date": {
            "type": "string",
            "format": "date-time"
          },
          "status": {
            "type": "string",
            "nullable": true
          },
          "buyIn": {
            "type": "number",
            "format": "double"
          },
          "fee": {
            "type": "number",
            "format": "double"
          },
          "guaranteed": {
            "type": "number",
            "format": "double"
          },
          "startingChips": {
            "type": "integer",
            "format": "int32"
          },
          "seating": {
            "$ref": "#/components/schemas/PokerGenys.Domain.Models.SeatingConfiguration"
          },
          "rebuyConfig": {
            "$ref": "#/components/schemas/PokerGenys.Domain.Models.RebuyConfig"
          },
          "addonConfig": {
            "$ref": "#/components/schemas/PokerGenys.Domain.Models.AddonConfig"
          },
          "bountyConfig": {
            "$ref": "#/components/schemas/PokerGenys.Domain.Models.BountyConfig"
          },
          "levels": {
            "type": "array",
            "items": {
              "$ref": "#/components/schemas/PokerGenys.Domain.Models.BlindLevel"
            },
            "nullable": true
          },
          "payouts": {
            "type": "array",
            "items": {
              "$ref": "#/components/schemas/PokerGenys.Domain.Models.PayoutTier"
            },
            "nullable": true
          },
          "registrations": {
            "type": "array",
            "items": {
              "$ref": "#/components/schemas/PokerGenys.Domain.Models.TournamentRegistration"
            },
            "nullable": true
          },
          "startTime": {
            "type": "string",
            "format": "date-time",
            "nullable": true
          },
          "currentLevel": {
            "type": "integer",
            "format": "int32"
          },
          "prizePool": {
            "type": "number",
            "format": "double"
          }
        },
        "additionalProperties": false
      },
      "PokerGenys.Domain.Models.TournamentRegistration": {
        "type": "object",
        "properties": {
          "id": {
            "type": "string",
            "format": "uuid"
          },
          "tournamentId": {
            "type": "string",
            "format": "uuid"
          },
          "playerId": {
            "type": "string",
            "nullable": true
          },
          "playerName": {
            "type": "string",
            "nullable": true
          },
          "memberId": {
            "type": "string",
            "nullable": true
          },
          "seatId": {
            "type": "string",
            "nullable": true
          },
          "tableId": {
            "type": "string",
            "nullable": true
          },
          "chips": {
            "type": "integer",
            "format": "int32"
          },
          "registrationType": {
            "type": "string",
            "nullable": true
          },
          "paidAmount": {
            "type": "number",
            "format": "double"
          },
          "paymentMethod": {
            "type": "string",
            "nullable": true
          },
          "registeredAt": {
            "type": "string",
            "format": "date-time"
          },
          "status": {
            "type": "string",
            "nullable": true
          },
          "eliminatedAt": {
            "type": "string",
            "format": "date-time",
            "nullable": true
          },
          "payoutAmount": {
            "type": "number",
            "format": "double",
            "nullable": true
          },
          "metadata": {
            "type": "object",
            "additionalProperties": { },
            "nullable": true
          }
        },
        "additionalProperties": false
      },
      "PokerGenys.Domain.Models.Transaction": {
        "type": "object",
        "properties": {
          "id": {
            "type": "string",
            "format": "uuid"
          },
          "sessionId": {
            "type": "string",
            "format": "uuid"
          },
          "type": {
            "$ref": "#/components/schemas/PokerGenys.Domain.Models.TransactionType"
          },
          "category": {
            "$ref": "#/components/schemas/PokerGenys.Domain.Models.TransactionCategory"
          },
          "amount": {
            "type": "number",
            "format": "double"
          },
          "paymentStatus": {
            "$ref": "#/components/schemas/PokerGenys.Domain.Models.PaymentStatus"
          },
          "paymentMethod": {
            "$ref": "#/components/schemas/PokerGenys.Domain.Models.PaymentMethod"
          },
          "bankMethod": {
            "$ref": "#/components/schemas/PokerGenys.Domain.Models.BankMethod"
          },
          "transferProof": {
            "type": "string",
            "nullable": true
          },
          "description": {
            "type": "string",
            "nullable": true
          },
          "createdAt": {
            "type": "string",
            "format": "date-time"
          }
        },
        "additionalProperties": false
      },
      "PokerGenys.Domain.Models.TransactionCategory": {
        "enum": [
          "Restaurant",
          "Other"
        ],
        "type": "string"
      },
      "PokerGenys.Domain.Models.TransactionType": {
        "enum": [
          "BuyIn",
          "ReBuy",
          "Sale",
          "CashOut",
          "Jackpot",
          "DebtPayment"
        ],
        "type": "string"
      }
    }
  }
}